{"ocr_results":[{"text":"报到中央文革小組，所以学习应抓两头，两头吃透了，就好办了，","box":[[110,213],[2635,111],[2639,214],[114,315]]},{"text":"若不注意这一点，你們就可能和先去的北京缸卫兵顶起来，他們会","box":[[122,379],[2692,283],[2696,369],[125,466]]},{"text":"你们是“保皇派”。“保皇派”看保什么皇我们指的是保走","box":[[110,499],[2684,408],[2688,510],[114,602]]},{"text":"本主义道路当权派的皇。是不是所有的领导部門都是走资本主义道","box":[[109,629],[2695,537],[2699,645],[113,737]]},{"text":"路的当权派不是，即使有的领导部門是走资本主义道路的当权派，","box":[[107,748],[2724,666],[2728,778],[111,860]]},{"text":"也不是每个都是，要不然，那不是毛主席领导下的中国也变为漆","box":[[127,882],[2694,808],[2697,905],[130,978]]},{"text":"黑一团了？只能是部分的，小量的。在《廿三条》中就时了这","box":[[125,1007],[2672,942],[2674,1039],[128,1105]]},{"text":"个間题，你們可以学习《廿三条。《十六条》中也回答了这个間","box":[[127,1138],[2670,1076],[2673,1168],[129,1230]]},{"text":"题，所以这个学习是經常性的工作，不仅要在火車上学，到了目的","box":[[132,1258],[2692,1208],[2693,1301],[134,1352]]},{"text":"地更要学。我与几个大学的筹委会过，起来，他们叫苦有时","box":[[129,1387],[2687,1346],[2688,1431],[130,1472]]},{"text":"間学，青年人成了忙忙碌碌的事务主义还行？不管怎样忙，每天都","box":[[131,1512],[2684,1476],[2685,1561],[132,1597]]},{"text":"要抽出一、二个钟头学习毛著，进行社会調查，要冷静分析。学习","box":[[131,1640],[2681,1605],[2682,1692],[132,1726]]},{"text":"是为了战平，至于放半年假从学校到社会这是一个更大的学校。","box":[[137,1765],[2626,1742],[2627,1823],[138,1846]]},{"text":"在这个革命斗争地点的关键时刻更应好好学习。","box":[[132,1890],[1915,1878],[1916,1958],[133,1970]]},{"text":"第三，你們是宣傅队。但不要变成工作粗，包办代替人家。二","box":[[310,2011],[2691,2010],[2691,2091],[310,2093]]},{"text":"个注意：不要做“保皇派”，不要变成新的工作粗。把北京的情况","box":[[139,2135],[2711,2136],[2711,2223],[139,2221]]},{"text":"做法，先跟北京去的同学交流，在战斗班讨之后再回答，不要冲","box":[[152,2261],[2690,2271],[2689,2346],[152,2336]]},{"text":"口而出，这也不对那也不对，这样就給人家对立起来了，这里对你","box":[[160,2373],[2685,2383],[2685,2484],[160,2474]]},{"text":"們更有信心一些。有信心是你們完成任务，不是你們不犯錯","box":[[165,2498],[2692,2523],[2691,2604],[165,2580]]},{"text":"首先和去上海回来的同学座谈，第二步和各地的叔卫兵交流經","box":[[348,2621],[2682,2653],[2681,2728],[347,2697]]},{"text":"，然后向社会做调查研究。你們去调查研究，你們去调查研究境","box":[[180,2737],[2675,2776],[2674,2851],[179,2812]]},{"text":"好不要妨碍他们的生产。他們的群众大会你們可以去参加，这很好，","box":[[187,2855],[2692,2898],[2690,2978],[185,2935]]},{"text":"来学习，你們調查，他们在厂外接待你们这可以。抓革命促生产的","box":[[187,2963],[2660,3018],[2657,3110],[185,3054]]},{"text":"社重点是拿重工人农民同志会解决自已的問题。农民从搞四消起，","box":[[189,3078],[2686,3139],[2683,3230],[187,3169]]},{"text":"根据四清布置，也会抓革命促生产，尤其三秋。因为从全国看今年","box":[[189,3200],[2666,3257],[2664,3353],[187,3296]]},{"text":"是一个好年成，我們积极参加三秋工作，帮助他们，到他們中開去","box":[[202,3320],[2648,3382],[2646,3469],[200,3406]]},{"text":"劳动，去学习。你們这个战斗队，不仅要参加社会的战斗，而且也","box":[[209,3434],[2639,3506],[2636,3591],[206,3518]]},{"text":"要向自然开战。我们准备再写一篇社，学生的革命由学生自已来","box":[[209,3544],[2647,3621],[2644,3712],[206,3635]]},{"text":"搞，相信学生教师会自已教育自己，自已来搞革命，工农不要干予，","box":[[217,3658],[2678,3732],[2675,3829],[214,3756]]},{"text":"主要是有些领导的粗織工农来打学生，目的是工农兵互相拿重","box":[[220,3778],[2632,3850],[2630,3942],[217,3869]]}],"dimensions":{"height":4000,"width":3000}}