{"ocr_results":[{"text":"有你的优势，我有我的优势，科学院有资产阶级肥沃土壤，不会长出","box":[[2569,271],[4575,300],[4574,401],[2568,372]]},{"text":"象十七年那样去培养学生，我看哪，这样下去，培养的学生也只","box":[[256,330],[2033,286],[2035,370],[258,414]]},{"text":"鲜花，你搞调查不挖这个行吗？一点点挖阶级基础，不挖进入共产主","box":[[2571,398],[4579,421],[4578,516],[2570,493]]},{"text":"能是对我国的经济基础啊，对我国生产力的发展，起极大的反作用，","box":[[131,449],[1987,413],[1989,493],[132,529]]},{"text":"大保##","box":[[1750,538],[2023,538],[2023,588],[1750,588]]},{"text":"义不可能······","box":[[2579,539],[2993,528],[2995,599],[2580,609]]},{"text":"破坏作用。","box":[[125,558],[397,565],[396,637],[123,631]]},{"text":"（肖剑秋一九七六年九月二十九日在三单位阶级斗争现状和历","box":[[3241,659],[4570,682],[4569,732],[3240,709]]},{"text":"（张铁生一九七六年二月十日在太原的讲话）","box":[[734,680],[1641,663],[1642,713],[735,730]]},{"text":"史调查座谈会上的讲话）","box":[[3268,739],[3796,747],[3795,797],[3267,789]]},{"text":"讲到教育阵地，教师都是国民党时期留下来的，我们没有自己的","box":[[244,786],[2027,782],[2027,857],[244,860]]},{"text":"教员，教授，以后靠我们才逐步培养了新的，但也是按照他们的思想","box":[[120,896],[2023,903],[2023,980],[120,972]]},{"text":"留苏学生是“戴红帽子的，难办”。","box":[[2722,897],[3739,905],[3738,972],[2721,964]]},{"text":"体系培养的，“基本照旧”，除了不喊蒋委员长万岁外，也差不多。","box":[[117,1017],[2022,1026],[2021,1095],[116,1085]]},{"text":"（乔林在一九七五年四月十一日汇报规划时的讲话）","box":[[3244,1022],[4350,1032],[4349,1084],[3244,1074]]},{"text":"（迟群、谢静宜一九七六年五月在清华大学机械系学习座谈会","box":[[728,1134],[2025,1149],[2025,1207],[727,1192]]},{"text":"上的讲话）","box":[[754,1212],[966,1216],[965,1270],[753,1266]]},{"text":"#老#工共自#","box":[[1576,1251],[2017,1265],[2015,1326],[1574,1312]]},{"text":"我宁肯要专政工具，不要红色工程师。","box":[[241,1365],[1256,1380],[1255,1442],[240,1426]]},{"text":"（三）反对又红又专，鼓吹知识越多越反动","box":[[2899,1389],[4305,1395],[4305,1464],[2898,1458]]},{"text":"（迟群的一次讲话。转摘自《资产阶级野心家迟群的反党罪行","box":[[724,1484],[2024,1507],[2023,1563],[723,1540]]},{"text":"必须彻底批判》，一九七七年九月七日《北京日报》）","box":[[748,1564],[1898,1589],[1897,1633],[747,1609]]},{"text":"一个是培育有资产阶级觉悟的有文化的剥削者、精神贵族，一个","box":[[2716,1622],[4567,1624],[4567,1687],[2716,1685]]},{"text":"如果说，科学院有它的特点，可以研究。······在这个战场上资产","box":[[226,1703],[2020,1745],[2019,1816],[225,1774]]},{"text":"是培养有觉悟的没有文化的劳动者，你说要什么人？我宁要一个没有","box":[[2581,1737],[4571,1743],[4571,1808],[2581,1802]]},{"text":"阶级的优势是什么呢？是“知识”。我们是唯物主义者，我们要认识","box":[[110,1815],[2018,1863],[2017,1931],[108,1884]]},{"text":"文化的劳动者，而不要一个有文化的剥削者、精神贵族。","box":[[2585,1858],[4195,1862],[4194,1925],[2585,1922]]},{"text":"这个现实。资产阶级也正是利用这个暂时优势，来同无产阶级对抗，","box":[[107,1927],[1963,1982],[1961,2051],[105,1996]]},{"text":"（张春桥的一次讲话。转摘自《资产阶级文化专制主义的卫道","box":[[3227,1981],[4571,1981],[4571,2026],[3227,2026]]},{"text":"争夺科研领导权，靠党内的走资派来实现他们的愿望，借此争夺下一","box":[[105,2040],[2011,2101],[2009,2170],[103,2109]]},{"text":"土》，一九七六年十二月十二日《光明日报》）","box":[[3253,2056],[4283,2056],[4283,2106],[3253,2106]]},{"text":"代；培养资产阶级接班人。这就是科学院阶级斗争的特点，这就是两","box":[[109,2152],[2011,2218],[2009,2287],[106,2221]]},{"text":"文化大革命打倒刘少奇、林彪，即使全国都成了文盲，也是最大","box":[[2717,2218],[4564,2214],[4564,2277],[2718,2281]]},{"text":"大阶级对垒敌方的态势。·…．逐步的夺取这块阵地，剥夺资产阶级占","box":[[104,2258],[2011,2330],[2008,2412],[101,2340]]},{"text":"的胜利。","box":[[2580,2324],[2806,2338],[2801,2411],[2576,2397]]},{"text":"有的暂时的“知识优势”，把这种“优势”逐步转移到无产阶级方面","box":[[106,2373],[2010,2451],[2006,2528],[102,2450]]},{"text":"#）午#","box":[[2599,2439],[3144,2449],[3143,2525],[2597,2515]]},{"text":"（张春桥的一次讲话。转摘自《彻底清算“四人帮”在教育界","box":[[3221,2454],[4564,2447],[4564,2497],[3222,2505]]},{"text":"来。我们改造科学院的任务是艰巨而光荣的。","box":[[113,2491],[1313,2541],[1311,2610],[110,2559]]},{"text":"的滔天罪行》，一九七六年十二月一日《文汇报》）","box":[[3247,2531],[4379,2525],[4379,2575],[3248,2581]]},{"text":"子十#","box":[[1467,2548],[1871,2565],[1869,2624],[1465,2608]]},{"text":"（柳忠阳、肖剑秋一九七六年九月二十八日炮制的《反击右倾","box":[[702,2627],[2013,2693],[2010,2749],[699,2682]]},{"text":"翻案风运动的总结》）","box":[[725,2705],[1180,2727],[1178,2777],[723,2755]]},{"text":"只要全国不出修正主义，全国都成了文盲也在所不惜。","box":[[2721,2696],[4250,2685],[4250,2748],[2722,2760]]},{"text":"（张春桥的一次讲话。转摘自《坚持又红又专的正确方向》，","box":[[3227,2806],[4523,2795],[4523,2851],[3227,2862]]},{"text":"科学院还有个最大的问题，依靠谁这个问题，有的人连讲也不敢","box":[[230,2829],[2004,2923],[2000,2999],[226,2906]]},{"text":"一九七七年五月六日《辽宁日报》）","box":[[3255,2888],[4024,2877],[4025,2925],[3255,2937]]},{"text":"讲，何况做，不做科学院是改造不了的。现在就出了个问题，稍有了","box":[[112,2937],[2001,3040],[1997,3115],[108,3012]]},{"text":"成就的知识分子，他消极了。这没有什么了不起，是暂时的，·……·你","box":[[110,3047],[2003,3156],[1998,3232],[106,3123]]},{"text":"过去大学生，从小学到大学要念一大堆书，他们说那是有用的，","box":[[2714,3050],[4504,3027],[4505,3098],[2714,3121]]},{"text":"不读是不行的。实际上学生考试完了就忘了。要是忘了还好些，受毒","box":[[2579,3166],[4554,3143],[4555,3217],[2580,3240]]},{"text":"—36—","box":[[944,3233],[1137,3245],[1133,3310],[940,3299]]},{"text":"——37—","box":[[3474,3300],[3670,3300],[3670,3359],[3474,3359]]}],"dimensions":{"height":3456,"width":4608}}